{
    "name": "tickets",
    "attrs": {
        "user": {
            "type": "id",
            "reference": {
                "type": "referenceOne",
                "collection": "users"
            },
            "permissions": {
                "fields": true,
                "conditions": true,
                "sort": true,
                "documents": {
                    "insert": true,
                    "update": true,
                    "delete": true
                }
            },
            "default": {
                "fields": true
            },
            "dataforapidoc": {
                "description": "aaaaaaaaaaaaaaaaa",
                "color": "red"
            }
        },
        "account": {
            "type": "id",
            "reference": {
                "type": "referenceOne",
                "collection": "accounts"
            },
            "permissions": {
                "fields": true,
                "conditions": true,
                "sort": true,
                "documents": {
                    "insert": true,
                    "update": true,
                    "delete": true
                }
            },
            "default": {
                "fields": true
            },
            "dataforapidoc": {
                "description": "aaaaaaaaaaaaaaaaa",
                "color": "red"
            }
        },
        "reason": {
            "type": "id",
            "reference": {
                "type": "picklist"
            },
            "permissions": {
                "fields": true,
                "conditions": true,
                "sort": true,
                "documents": {
                    "insert": true,
                    "update": true,
                    "delete": true
                }
            },
            "default": {
                "fields": true
            },
            "dataforapidoc": {
                "description": "aaaaaaaaaaaaaaaaa",
                "color": "red"
            }
        },
        "subject": {
            "type": "string",
            "permissions": {
                "fields": true,
                "conditions": true,
                "sort": true,
                "documents": {
                    "insert": true,
                    "update": true,
                    "delete": true
                }
            },
            "default": {
                "fields": true
            },
            "dataforapidoc": {
                "description": "aaaaaaaaaaaaaaaaa",
                "color": "red"
            }
        },
        "content": {
            "type": "string",
            "permissions": {
                "fields": true,
                "conditions": true,
                "sort": true,
                "documents": {
                    "insert": true,
                    "update": true,
                    "delete": true
                }
            },
            "default": {
                "fields": true
            },
            "dataforapidoc": {
                "description": "aaaaaaaaaaaaaaaaa",
                "color": "red"
            }
        },
        "state": {
            "type": "string",
            "permissions": {
                "fields": true,
                "conditions": true,
                "sort": true,
                "documents": {
                    "insert": true,
                    "update": true,
                    "delete": true
                }
            },
            "default": {
                "fields": true
            },
            "dataforapidoc": {
                "description": "aaaaaaaaaaaaaaaaa",
                "color": "red"
            }
        }
    }
}